<?xml version="1.0" encoding="UTF-8"?>
<!DOCTYPE mapper PUBLIC "-//mybatis.org//DTD Mapper 3.0//EN" "http://mybatis.org/dtd/mybatis-3-mapper.dtd">
<mapper namespace="com.bjsxt.nw185.dao.RoleEmpDAO">

	<insert id="insert" parameterType="com.bjsxt.nw185.entity.RoleEmp">
		INSERT INTO t_role_emp (emp_id,role_id)
		VALUES (#{empId},#{roleId})
	</insert>
	
	<update id="update" parameterType="com.bjsxt.nw185.entity.RoleEmp">
		UPDATE t_role_emp
			SET  
				ru_id = #{ruId}
				,emp_id = #{empId}
				,role_id = #{roleId}
			WHERE ru_id = #{ruId}
			
	</update>
	
	<delete id="delete" parameterType="Integer">
		DELETE FROM t_role_emp where ru_id = #{value}
	</delete>
	
	<select id="findById" parameterType="Integer" resultType="com.bjsxt.nw185.entity.RoleEmp">
		select
				t.ru_id ruId ,
				t.emp_id empId ,
				t.role_id roleId 
		from t_role_emp t where t.ru_id = #{value}
	</select>
	
	<select id="findByProperty" parameterType="java.util.Map"   resultType="java.util.LinkedHashMap">
		select 
				t.ru_id ruId ,
				t.emp_id empId ,
				t.role_id roleId 
		 from t_role_emp t where 1=1 
		<if test="ruId != null">
		and t.ru_id =#{ruId}
		</if>
		<if test="empId != null">
		and t.emp_id =#{empId}
		</if>
		<if test="roleId != null">
		and t.role_id =#{roleId}
		</if>
		<if test="st != null and r != null">
			limit #{st} , #{r}
		</if>
	</select>

	<select id="countByProperty" parameterType="java.util.Map"   resultType="Long">
		select count(*) cnt from t_role_emp t where 1=1 
		<if test="ruId != null">
		and t.ru_id =#{ruId}
		</if>
		<if test="empId != null">
		and t.emp_id =#{empId}
		</if>
		<if test="roleId != null">
		and t.role_id =#{roleId}
		</if>
	</select>

</mapper>